{
  "_class": "symbolInstance",
  "booleanOperation": -1,
  "clippingMaskMode": 0,
  "do_objectID": "024446BF-6229-41D1-A643-9452BF36A06D",
  "exportOptions": {
    "_class": "exportOptions",
    "do_objectID": "812AF631-A015-42AD-B838-323F42084F08",
    "exportFormats": [
    ],
    "includedLayerIds": [
    ],
    "layerOptions": 0,
    "shouldTrim": false
  },
  "frame": {
    "_class": "rect",
    "constrainProportions": false,
    "do_objectID": "0D0E8712-1688-4FEF-8881-DE68DCEC0F19",
    "height": 48,
    "width": 48,
    "x": 48,
    "y": 152
  },
  "hasClippingMask": false,
  "horizontalSpacing": 0,
  "isFixedToViewport": false,
  "isFlippedHorizontal": false,
  "isFlippedVertical": false,
  "isLocked": false,
  "isVisible": true,
  "layerListExpandedType": 0,
  "name": "btn / fill / brand_10",
  "nameIsFixed": true,
  "overrideValues": [
  ],
  "resizingConstraint": 63,
  "resizingType": 0,
  "rotation": 0,
  "scale": 1,
  "shouldBreakMaskChain": false,
  "style": {
    "_class": "style",
    "do_objectID": "7E7EBEF6-CF91-42EF-873F-19722F5D36FD",
    "endMarkerType": 0,
    "miterLimit": 10,
    "startMarkerType": 0,
    "windingRule": 1
  },
  "symbolID": "67422352-93B6-4500-BD9E-DC8531E37D1B",
  "verticalSpacing": 0
}