{
  "_class": "symbolInstance",
  "booleanOperation": -1,
  "clippingMaskMode": 0,
  "do_objectID": "E9B3BBF5-9384-4B05-9135-B74AAF97D66B",
  "exportOptions": {
    "_class": "exportOptions",
    "do_objectID": "64164836-485A-46EC-95F6-06A77B680641",
    "exportFormats": [
      {
        "_class": "exportFormat",
        "absoluteSize": 0,
        "fileFormat": "png",
        "name": "",
        "namingScheme": 0,
        "scale": 1,
        "visibleScaleType": 0
      },
      {
        "_class": "exportFormat",
        "absoluteSize": 0,
        "fileFormat": "png",
        "name": "@2x",
        "namingScheme": 0,
        "scale": 2,
        "visibleScaleType": 0
      },
      {
        "_class": "exportFormat",
        "absoluteSize": 0,
        "fileFormat": "png",
        "name": "@3x",
        "namingScheme": 0,
        "scale": 3,
        "visibleScaleType": 0
      }
    ],
    "includedLayerIds": [
    ],
    "layerOptions": 0,
    "shouldTrim": false
  },
  "frame": {
    "_class": "rect",
    "constrainProportions": false,
    "do_objectID": "464F718A-FBD2-47F2-BACB-781240ED5475",
    "height": 48,
    "width": 375,
    "x": 0,
    "y": 20
  },
  "hasClippingMask": false,
  "horizontalSpacing": 0,
  "isFixedToViewport": false,
  "isFlippedHorizontal": false,
  "isFlippedVertical": false,
  "isLocked": false,
  "isVisible": true,
  "layerListExpandedType": 0,
  "name": "header / calendarToday",
  "nameIsFixed": true,
  "overrideValues": [
    {
      "_class": "overrideValue",
      "do_objectID": "5A7449E3-C126-44A8-A55B-D0A62FAF58A3",
      "overrideName": "6B2839D0-BFEE-41D6-AC88-72F8156B0C39_symbolID",
      "value": ""
    },
    {
      "_class": "overrideValue",
      "do_objectID": "0237265A-9176-4C38-ADFB-5ABAEBDBDB8E",
      "overrideName": "B8693FBB-7A5D-4927-89B0-19C4D896BF2F_stringValue",
      "value": "2019년 6월"
    }
  ],
  "resizingConstraint": 63,
  "resizingType": 0,
  "rotation": 0,
  "scale": 1,
  "shouldBreakMaskChain": false,
  "style": {
    "_class": "style",
    "do_objectID": "8EB7FFC0-2AA9-4903-9348-89CACF45589C",
    "endMarkerType": 0,
    "miterLimit": 10,
    "startMarkerType": 0,
    "windingRule": 1
  },
  "symbolID": "5875DA76-DAD0-4318-9B62-0555F0B4CEEA",
  "verticalSpacing": 0
}